[
  {
    "id": 0,
    "name": "FNM Ancestral Hoodie",
    "picture": "images/scottish-terrier.png",
    "age": 50,
    "breed": "Uk Shipping",
    "location": "Lisco, Alabama"
  },
  {
    "id": 1,
    "name": "Product 2",
    "picture": "images/scottish-terrier.png",
    "age": 3,
    "breed": "Scottish Terrier",
    "location": "Tooleville, West Virginia"
  },
  {
    "id": 2,
    "name": "Product 2",
    "picture": "images/french-bulldog.png",
    "age": 2,
    "breed": "French Bulldog",
    "location": "Freeburn, Idaho"
  },
  {
    "id": 3,
    "name": "Product 2",
    "picture": "images/boxer.png",
    "age": 2,
    "breed": "Boxer",
    "location": "Camas, Pennsylvania"
  },
  {
    "id": 4,
    "name": "Product 2",
    "picture": "images/french-bulldog.png",
    "age": 2,
    "breed": "French Bulldog",
    "location": "Gerber, South Dakota"
  },
  {
    "id": 5,
    "name": "Product 2",
    "picture": "images/french-bulldog.png",
    "age": 3,
    "breed": "French Bulldog",
    "location": "Innsbrook, Illinois"
  },
  {
    "id": 6,
    "name": "Product 2",
    "picture": "images/golden-retriever.png",
    "age": 3,
    "breed": "Golden Retriever",
    "location": "Soudan, Louisiana"
  },
  {
    "id": 7,
    "name": "Product 2",
    "picture": "images/golden-retriever.png",
    "age": 3,
    "breed": "Golden Retriever",
    "location": "Jacksonwald, Palau"
  },
  {
    "id": 8,
    "name": "Product 2",
    "picture": "images/french-bulldog.png",
    "age": 2,
    "breed": "French Bulldog",
    "location": "Honolulu, Hawaii"
  },
  {
    "id": 9,
    "name": "Product 2",
    "picture": "images/boxer.png",
    "age": 3,
    "breed": "Product 2",
    "location": "Matheny, Utah"
  },
  {
    "id": 10,
    "name": "Product 2",
    "picture": "images/boxer.png",
    "age": 2,
    "breed": "Boxer",
    "location": "Tyhee, Indiana"
  },
  {
    "id": 11,
    "name": "Product 2",
    "picture": "images/scottish-terrier.png",
    "age": 3,
    "breed": "Scottish Terrier",
    "location": "Windsor, Montana"
  },
  {
    "id": 12,
    "name": "Product 2",
    "picture": "images/french-bulldog.png",
    "age": 3,
    "breed": "French Bulldog",
    "location": "Kingstowne, Nevada"
  },
  {
    "id": 13,
    "name": "Product 2",
    "picture": "images/golden-retriever.png",
    "age": 4,
    "breed": "Golden Retriever",
    "location": "Sultana, Massachusetts"
  },
  {
    "id": 14,
    "name": "Product 2",
    "picture": "images/golden-retriever.png",
    "age": 2,
    "breed": "Golden Retriever",
    "location": "Broadlands, Oregon"
  },
  {
    "id": 15,
    "name": "Product 2",
    "picture": "images/golden-retriever.png",
    "age": 2,
    "breed": "Golden Retriever",
    "location": "Dawn, Wisconsin"
  },
  {
    "id": 16,
    "name": "Product 2",
    "picture": "images/golden-retriever.png",
    "age": 2,
    "breed": "Golden Retriever",
    "location": "Dawne, Wisconsine"
  },
  {
    "id": 17,
    "name": "Product 2",
    "picture": "images/golden-retriever.png",
    "age": 2,
    "breed": "Golden Retriever",
    "location": "Dawne, Wisconsine"
  }
]
